xaj/DP5.py
xaj/NR.py
xaj/RK4.py
xaj/__init__.py
xaj/core.py
xaj/pace.py
xaj/trek.py
xaj-0.1.8.dist-info/LICENSE
xaj-0.1.8.dist-info/METADATA
xaj-0.1.8.dist-info/WHEEL
xaj-0.1.8.dist-info/top_level.txt
xaj-0.1.8.dist-info/RECORD
