Metadata-Version: 2.1
Name: xaj
Version: 0.1.8
Summary: ODE integrator for JAX
Home-page: https://github.com/adxsrc/xaj
Author: Chi-kwan Chan
Author-email: chanc@arizona.edu
Requires-Python: >=3.7,<3.12
License-File: LICENSE
Requires-Dist: jaxlib <0.4,>=0.3
Requires-Dist: jax <0.4,>=0.3
Requires-Dist: tqdm
